photofind/__init__.py
photofind/photofind.py
photofind/version.py
photofind-1.1.1.data/data/VERSION
photofind-1.1.1.dist-info/LICENSE
photofind-1.1.1.dist-info/METADATA
photofind-1.1.1.dist-info/WHEEL
photofind-1.1.1.dist-info/entry_points.txt
photofind-1.1.1.dist-info/top_level.txt
photofind-1.1.1.dist-info/RECORD
