Metadata-Version: 2.1
Name: photofind
Version: 1.1.1
Summary: read filenames and output EXIF data from named files
Home-page: https://github.com/rstms/photofind
Author: Matt Krueger
Author-email: mkrueger@rstms.net
License: MIT
Keywords: exif photo image
Platform: UNKNOWN
Classifier: Programming Language :: Python :: 2.7
Classifier: Programming Language :: Python :: 3
Classifier: License :: OSI Approved :: MIT License
Classifier: Operating System :: OS Independent
Classifier: Environment :: Console
Requires-Dist: Click
Requires-Dist: ExifRead
Requires-Dist: geopy
